setup.py
sympy_recursive/__init__.py
sympy_recursive.egg-info/PKG-INFO
sympy_recursive.egg-info/SOURCES.txt
sympy_recursive.egg-info/dependency_links.txt
sympy_recursive.egg-info/not-zip-safe
sympy_recursive.egg-info/requires.txt
sympy_recursive.egg-info/top_level.txt