Metadata-Version: 1.0
Name: sympy-recursive
Version: 0.1.1
Summary: Resolve recursive sequences to explicit nth item formulas with SymPy.
Home-page: http://github.com/hejmsdz/sympy_recursive
Author: Mikołaj Rozwadowski
Author-email: mikolaj.rozwadowski@outlook.com
License: MIT
Platform: UNKNOWN
